{
  "name": "Sunken Tribune Focus",
  "icon": "goety_cataclysm:sunken_tribune_focus",
  "category": "goety:cataclysm/focuses/abyss",
  "pages": [
    {
      "type": "patchouli:text",
      "text": "The spell calls forth a Deepling spellcaster from the very depths. One can expect either a Priest or a Warlock to answer your call."
    },
    {
      "type": "goety:ritual",
      "recipe": "goety_cataclysm:focus/sunken_tribune_focus"
    }
  ],
  "extra_recipe_mappings": {
    "goety_cataclysm:sunken_tribune_focus": 1
  }
}